src/izandescriptive_library/__init__.py
src/izandescriptive_library/class_descriptives.py
izandescriptive-0.0.2.dist-info/METADATA
izandescriptive-0.0.2.dist-info/WHEEL
izandescriptive-0.0.2.dist-info/licenses/LICENSE
izandescriptive-0.0.2.dist-info/RECORD
