Metadata-Version: 2.1
Name: izandescriptive
Version: 0.0.2
Summary: This library generates different graphics of numerical variables from a csv file.
Project-URL: Homepage, https://github.com/ceciliabilbao/izandescriptive
Project-URL: Bug Tracker, https://github.com/ceciliabilbao/izandescriptive/issues
Author-email: Irene Cecilia <irene.herrera@alumni.mondragon.edu>
License-File: LICENSE
Classifier: License :: OSI Approved :: MIT License
Classifier: Operating System :: OS Independent
Classifier: Programming Language :: Python :: 3
Requires-Python: >=3.7
